LICENSE
MANIFEST.in
README.md
pyproject.toml
requirements.txt
setup.py
src/grounds/__init__.py
src/grounds/__main__.py
src/grounds.egg-info/PKG-INFO
src/grounds.egg-info/SOURCES.txt
src/grounds.egg-info/dependency_links.txt
src/grounds.egg-info/entry_points.txt
src/grounds.egg-info/requires.txt
src/grounds.egg-info/top_level.txt
src/grounds/rice/__init__.py
src/grounds/rice/rice_ext.pyx