Metadata-Version: 2.1
Name: grounds
Version: 0.1
Summary: Fast entropy coder for Python
Home-page: https://github.com/KLZ-0/grounds/
Author: KLZ-0
Author-email: adrian@kalazi.com
Classifier: Programming Language :: Python :: 3
Classifier: License :: OSI Approved :: MIT License
Classifier: Operating System :: OS Independent
Requires-Python: >=3.6
License-File: LICENSE
